fuckvkeypad/__init__.py
fuckvkeypad/fuckvkeypad.py
fuckvkeypad/studio.py
fuckvkeypad-0.2.0.dist-info/LICENSE
fuckvkeypad-0.2.0.dist-info/METADATA
fuckvkeypad-0.2.0.dist-info/WHEEL
fuckvkeypad-0.2.0.dist-info/entry_points.txt
fuckvkeypad-0.2.0.dist-info/top_level.txt
fuckvkeypad-0.2.0.dist-info/RECORD
