Metadata-Version: 2.1
Name: fuckvkeypad
Version: 0.2.0
Summary: Bypassing vKeyboard using OpenCV
Home-page: https://github.com/soulee-dev/fuckvkeypad
Author: Soul Lee
License: MIT License
Platform: OS Independent
Classifier: Programming Language :: Python :: 3
License-File: LICENSE
Requires-Dist: click (==8.1.3)
Requires-Dist: colorama (==0.4.6)
Requires-Dist: mypy-extensions (==1.0.0)
Requires-Dist: numpy (==1.24.2)
Requires-Dist: opencv-contrib-python (==4.7.0.72)
Requires-Dist: packaging (==23.0)
Requires-Dist: pathspec (==0.11.1)
Requires-Dist: platformdirs (==3.2.0)
Requires-Dist: scipy (==1.10.1)
Requires-Dist: svgpathtools (==1.6.0)
Requires-Dist: svgwrite (==1.4.3)
Requires-Dist: tomli (==2.0.1)
